{
  "Participantes": [
    {
      "Nombre": "\u0110uro Ivkov",
      "Epiteto": "El Fuerte",
      "Edad": 81,
      "Clase": "Guerrero",
      "Caracteristicas": {
        "Velocidad": 3,
        "Destreza": 3,
        "Fuerza": 4,
        "Armadura": 5,
        "Salud": 100,
        "Magia": 0
      },
      "Nivel": 1
    },
    {
      "Nombre": "Otto \u00D8stenstad",
      "Epiteto": "El Valiente",
      "Edad": 134,
      "Clase": "Druida",
      "Caracteristicas": {
        "Velocidad": 5,
        "Destreza": 2,
        "Fuerza": 4,
        "Armadura": 3,
        "Salud": 100,
        "Magia": 4
      },
      "Nivel": 1
    },
    {
      "Nombre": "Jort Koenraadt",
      "Epiteto": "El Noble",
      "Edad": 288,
      "Clase": "Druida",
      "Caracteristicas": {
        "Velocidad": 3,
        "Destreza": 2,
        "Fuerza": 2,
        "Armadura": 2,
        "Salud": 100,
        "Magia": 5
      },
      "Nivel": 1
    },
    {
      "Nombre": "Tim\u00F3teo Vieira",
      "Epiteto": "El Noble",
      "Edad": 201,
      "Clase": "Mago",
      "Caracteristicas": {
        "Velocidad": 3,
        "Destreza": 3,
        "Fuerza": 2,
        "Armadura": 4,
        "Salud": 100,
        "Magia": 6
      },
      "Nivel": 1
    },
    {
      "Nombre": "Alexis Grewal",
      "Epiteto": "El Valiente",
      "Edad": 225,
      "Clase": "Mago",
      "Caracteristicas": {
        "Velocidad": 1,
        "Destreza": 3,
        "Fuerza": 2,
        "Armadura": 3,
        "Salud": 100,
        "Magia": 6
      },
      "Nivel": 1
    },
    {
      "Nombre": "Michelle Young",
      "Epiteto": "El Valiente",
      "Edad": 57,
      "Clase": "Guerrero",
      "Caracteristicas": {
        "Velocidad": 3,
        "Destreza": 3,
        "Fuerza": 4,
        "Armadura": 5,
        "Salud": 100,
        "Magia": 0
      },
      "Nivel": 1
    },
    {
      "Nombre": "Priyanka Kumar",
      "Epiteto": "El Sabio",
      "Edad": 250,
      "Clase": "Picaro",
      "Caracteristicas": {
        "Velocidad": 5,
        "Destreza": 4,
        "Fuerza": 2,
        "Armadura": 3,
        "Salud": 100,
        "Magia": 0
      },
      "Nivel": 1
    },
    {
      "Nombre": "\u0622\u0631\u0634 \u06A9\u0648\u062A\u06CC",
      "Epiteto": "El Fuerte",
      "Edad": 245,
      "Clase": "Mago",
      "Caracteristicas": {
        "Velocidad": 1,
        "Destreza": 3,
        "Fuerza": 2,
        "Armadura": 3,
        "Salud": 100,
        "Magia": 7
      },
      "Nivel": 1
    }
  ],
  "RondaActual": 0,
  "FaseTorneo": "cuartos"
}